{
    "data": [
        {
            "xs": {
                "x": 134,
                "y": 61.44000244140625
            },
            "ys": {
                "label": "C"
            }
        },
        {
            "xs": {
                "x": 127,
                "y": 141.44000244140625
            },
            "ys": {
                "label": "C"
            }
        },
        {
            "xs": {
                "x": 121,
                "y": 228.44000244140625
            },
            "ys": {
                "label": "C"
            }
        },
        {
            "xs": {
                "x": 441,
                "y": 55.44000244140625
            },
            "ys": {
                "label": "D"
            }
        },
        {
            "xs": {
                "x": 432,
                "y": 142.44000244140625
            },
            "ys": {
                "label": "D"
            }
        },
        {
            "xs": {
                "x": 425,
                "y": 219.44000244140625
            },
            "ys": {
                "label": "D"
            }
        },
        {
            "xs": {
                "x": 418,
                "y": 302.44000244140625
            },
            "ys": {
                "label": "D"
            }
        },
        {
            "xs": {
                "x": 490,
                "y": 277.44000244140625
            },
            "ys": {
                "label": "E"
            }
        },
        {
            "xs": {
                "x": 459,
                "y": 361.44000244140625
            },
            "ys": {
                "label": "E"
            }
        },
        {
            "xs": {
                "x": 527,
                "y": 365.44000244140625
            },
            "ys": {
                "label": "E"
            }
        },
        {
            "xs": {
                "x": 560,
                "y": 295.44000244140625
            },
            "ys": {
                "label": "E"
            }
        },
        {
            "xs": {
                "x": 408,
                "y": 260.44000244140625
            },
            "ys": {
                "label": "E"
            }
        },
        {
            "xs": {
                "x": 383,
                "y": 342.44000244140625
            },
            "ys": {
                "label": "E"
            }
        }
    ]
}